danticenvtk/__init__.py
danticenvtk/env.py
danticenvtk/run.py
danticenvtk-1.0.1.dist-info/WHEEL
danticenvtk-1.0.1.dist-info/METADATA
danticenvtk-1.0.1.dist-info/RECORD
