Metadata-Version: 2.1
Name: danticenvtk
Version: 1.0.1
Summary: toolkit
License: MIT
Author: wayfaring-stranger
Author-email: zw6p226m@duck.com
Requires-Python: >=3.7,<4.0
Classifier: License :: OSI Approved :: MIT License
Classifier: Programming Language :: Python :: 3
Classifier: Programming Language :: Python :: 3.7
Classifier: Programming Language :: Python :: 3.8
Classifier: Programming Language :: Python :: 3.9
Classifier: Programming Language :: Python :: 3.10
Classifier: Programming Language :: Python :: 3.11
